randpin/__init__.py
randpin/__main__.py
randpin/version.py
randpin-0.3.1.post1.dist-info/LICENCE
randpin-0.3.1.post1.dist-info/METADATA
randpin-0.3.1.post1.dist-info/WHEEL
randpin-0.3.1.post1.dist-info/entry_points.txt
randpin-0.3.1.post1.dist-info/top_level.txt
randpin-0.3.1.post1.dist-info/RECORD
