Metadata-Version: 2.1
Name: randpin
Version: 0.3.1.post1
Summary: A simple tool for opening a random unread bookmark from Pinboard
Home-page: https://github.com/avacariu/randpin
Author: Andrei Vacariu
Author-email: andrei@vacariu.ca
License: UNKNOWN
Platform: UNKNOWN
Classifier: Environment :: Console
Classifier: License :: OSI Approved :: MIT License
Classifier: Programming Language :: Python :: 3
Requires-Python: >=3.5
Requires-Dist: click
Requires-Dist: pinboard
